polls/__init__.py
polls/admin.py
polls/apps.py
polls/models.py
polls/tests.py
polls/urls.py
polls/views.py
polls/migrations/0001_initial.py
polls/migrations/__init__.py
polls/static/polls/style.css
polls/static/polls/images/background.gif
polls/templates/admin/base_site.html
polls/templates/polls/detail.html
polls/templates/polls/index.html
polls/templates/polls/results.html
django_polls02-0.6.dist-info/LICENSE
django_polls02-0.6.dist-info/METADATA
django_polls02-0.6.dist-info/WHEEL
django_polls02-0.6.dist-info/top_level.txt
django_polls02-0.6.dist-info/RECORD
